eldf.py
thindf.py
eldf-2021.2.1.dist-info/LICENSE.txt
eldf-2021.2.1.dist-info/METADATA
eldf-2021.2.1.dist-info/WHEEL
eldf-2021.2.1.dist-info/top_level.txt
eldf-2021.2.1.dist-info/RECORD
