Metadata-Version: 2.1
Name: eldf
Version: 2021.2.1
Summary: A Python implementation of ELDF data format
Home-page: https://eldf.org
Author: Alexander Tretyak
Author-email: alextretyak@users.noreply.github.com
License: MIT
Download-URL: https://sourceforge.net/p/eldf/code/ci/default/tarball
Platform: UNKNOWN
Classifier: Development Status :: 5 - Production/Stable
Classifier: Operating System :: OS Independent
Classifier: Programming Language :: Python
Classifier: License :: OSI Approved :: MIT License
